liquid_audio/__init__.py
liquid_audio/demo/__init__.py
liquid_audio/demo/chat.py
liquid_audio/demo/model.py
liquid_audio/detokenizer.py
liquid_audio/model/__init__.py
liquid_audio/model/conformer/__init__.py
liquid_audio/model/conformer/encoder.py
liquid_audio/model/conformer/mha.py
liquid_audio/model/conformer/modules.py
liquid_audio/model/conformer/processor.py
liquid_audio/model/conformer/subsampling.py
liquid_audio/model/conformer/utils.py
liquid_audio/model/lfm2_audio.py
liquid_audio/model/mlp.py
liquid_audio/model/transformer.py
liquid_audio/moshi/__init__.py
liquid_audio/moshi/client.py
liquid_audio/moshi/client_gradio.py
liquid_audio/moshi/client_utils.py
liquid_audio/moshi/conditioners/__init__.py
liquid_audio/moshi/conditioners/base.py
liquid_audio/moshi/conditioners/tensors.py
liquid_audio/moshi/conditioners/text.py
liquid_audio/moshi/models/__init__.py
liquid_audio/moshi/models/compression.py
liquid_audio/moshi/models/lm.py
liquid_audio/moshi/models/lm_utils.py
liquid_audio/moshi/models/loaders.py
liquid_audio/moshi/models/tts.py
liquid_audio/moshi/modules/__init__.py
liquid_audio/moshi/modules/conv.py
liquid_audio/moshi/modules/conv_test.py
liquid_audio/moshi/modules/gating.py
liquid_audio/moshi/modules/lora.py
liquid_audio/moshi/modules/resample.py
liquid_audio/moshi/modules/rope.py
liquid_audio/moshi/modules/seanet.py
liquid_audio/moshi/modules/seanet_test.py
liquid_audio/moshi/modules/streaming.py
liquid_audio/moshi/modules/transformer.py
liquid_audio/moshi/py.typed
liquid_audio/moshi/quantization/__init__.py
liquid_audio/moshi/quantization/base.py
liquid_audio/moshi/quantization/core_vq.py
liquid_audio/moshi/quantization/vq.py
liquid_audio/moshi/run_inference.py
liquid_audio/moshi/run_tts.py
liquid_audio/moshi/server.py
liquid_audio/moshi/utils/__init__.py
liquid_audio/moshi/utils/autocast.py
liquid_audio/moshi/utils/compile.py
liquid_audio/moshi/utils/quantize.py
liquid_audio/moshi/utils/sampling.py
liquid_audio/moshi/utils/utils.py
liquid_audio-1.1.0.dist-info/licenses/LICENSE
liquid_audio-1.1.0.dist-info/WHEEL
liquid_audio-1.1.0.dist-info/entry_points.txt
liquid_audio-1.1.0.dist-info/METADATA
liquid_audio-1.1.0.dist-info/RECORD
