Metadata-Version: 2.4
Name: liquid-audio
Version: 1.1.0
Summary: Liquid Audio - Speech-to-Speech audio models
Keywords: Liquid AI,LFM,LFM2,Audio,Speech-to-Speech
Author: Liquid AI, Inc
Author-email: Liquid AI, Inc <support@liquid.ai>
License-Expression: LicenseRef-LFM-Open-License-v1.0
License-File: LICENSE
Requires-Dist: accelerate>=1.10.1
Requires-Dist: einops>=0.8.1
Requires-Dist: librosa>=0.11.0
Requires-Dist: sentencepiece>=0.2.1
Requires-Dist: torch>=2.8.0
Requires-Dist: torchaudio>=2.8.0
Requires-Dist: torchcodec>=0.9.1
Requires-Dist: transformers>=4.55.4
Requires-Dist: fastrtc[vad]>=0.0.30 ; extra == 'demo'
Requires-Python: >=3.12
Project-URL: Homepage, https://www.liquid.ai/
Project-URL: Issues, https://github.com/Liquid4All/liquid-audio/issues
Project-URL: Repository, https://github.com/Liquid4All/liquid-audio/
Provides-Extra: demo
